clusterysis/__init__.py
clusterysis/view.py
clusterysis-1.0.3.dist-info/METADATA
clusterysis-1.0.3.dist-info/WHEEL
clusterysis-1.0.3.dist-info/top_level.txt
clusterysis-1.0.3.dist-info/RECORD
