Metadata-Version: 2.1
Name: clusterysis
Version: 1.0.3
Summary: A library for visualizing clusters.
Home-page: https://github.com/gabrieldi95/clusterysis
Author: Gabriel Di Pardi Arruda
License: UNKNOWN
Platform: UNKNOWN
Requires-Dist: pandas
Requires-Dist: plotly
Requires-Dist: matplotlib
